[{"date_last_updated":1329710745,"feed_baseurl":"http://trilliumtransit.com/transit_feeds/sfbay-ferries-ca-us/","name":"Alameda/Oakland Ferry","area":"San Francisco Bay Area","url":"http://www.eastbayferry.com/","country":"United States","state":"California","license_url":"","dataexchange_url":"http://www.gtfs-data-exchange.com/agency/alamedaoakland-ferry/","date_added":1252464905,"is_official":1,"dataexchange_id":"alamedaoakland-ferry","current_datafile":"sfbay-ferries-ca-us-archiver_20120220_0405","id":1,"createdAt":"2013-10-15T20:51:19.000Z","updatedAt":"2013-10-15T20:51:19.000Z"},{"date_last_updated":1377877685,"feed_baseurl":"http://data.cabq.gov/transit/gtfs/google_transit.zip","name":"ABQ Ride","area":"Albuquerque","url":"http://myabqride.com","country":"United States","state":"New Mexico","license_url":"","dataexchange_url":"http://www.gtfs-data-exchange.com/agency/abq-ride/","date_added":1340739867,"is_official":1,"dataexchange_id":"abq-ride","current_datafile":"abq-ride_20130830_1548","id":2,"createdAt":"2013-10-15T20:51:19.000Z","updatedAt":"2013-10-15T20:51:19.000Z"},{"date_last_updated":1372150471,"feed_baseurl":"http://www.actransit.org/google-transit-feed-specification/?did=5","name":"AC Transit","area":"","url":"http://www.actransit.org","country":"United States","state":"California","license_url":"http://www.actransit.org/data-terms-and-conditions/","dataexchange_url":"http://www.gtfs-data-exchange.com/agency/ac-transit/","date_added":1312587614,"is_official":1,"dataexchange_id":"ac-transit","current_datafile":"ac-transit_20130625_0854","id":3,"createdAt":"2013-10-15T20:51:19.000Z","updatedAt":"2013-10-15T20:51:19.000Z"},{"date_last_updated":1319598950,"feed_baseurl":"http://mta.maryland.gov/business/publicgtfsdata.cfm","name":"Annapolis Transit","area":"Annapolis","url":"http://www.annapolis.gov/government/departments/transportation.aspx","country":"United States","state":"Maryland","license_url":"","dataexchange_url":"http://www.gtfs-data-exchange.com/agency/annapolis-transit/","date_added":1297654991,"is_official":1,"dataexchange_id":"annapolis-transit","current_datafile":"mta-maryland-archiver_20111026_0315","id":4,"createdAt":"2013-10-15T20:51:20.000Z","updatedAt":"2013-10-15T20:51:20.000Z"},{"date_last_updated":1378949743,"feed_baseurl":"http://trilliumtransit.com/transit_feeds/humboldtcounty-ca-us/","name":"Arcata & Mad River Transit System","area":"Humboldt County","url":"http://www.arcatatransit.org/","country":"United States","state":"California","license_url":"","dataexchange_url":"http://www.gtfs-data-exchange.com/agency/arcata-mad-river-transit-system/","date_added":1225261819,"is_official":1,"dataexchange_id":"arcata-mad-river-transit-system","current_datafile":"humboldt-archiver_20130912_0135","id":5,"createdAt":"2013-10-15T20:51:21.000Z","updatedAt":"2013-10-15T20:51:21.000Z"},{"date_last_updated":1319598950,"feed_baseurl":"http://mta.maryland.gov/business/publicgtfsdata.cfm","name":"BWI Thurgood Marshall Intl Airport","area":"","url":"http://www.bwiairport.com","country":"United States","state":"Maryland","license_url":"","dataexchange_url":"http://www.gtfs-data-exchange.com/agency/bwi-thurgood-marshall-intl-airport/","date_added":1297654990,"is_official":1,"dataexchange_id":"bwi-thurgood-marshall-intl-airport","current_datafile":"mta-maryland-archiver_20111026_0315","id":6,"createdAt":"2013-10-15T20:51:21.000Z","updatedAt":"2013-10-15T20:51:21.000Z"},{"date_last_updated":1381725065,"feed_baseurl":"http://www.arlingtontransit.com/gtfs/google_transit.zip","name":"Arlington Transit","area":"","url":"http://www.arlingtontransit.com","country":"United States","state":"Virginia","license_url":"","dataexchange_url":"http://www.gtfs-data-exchange.com/agency/arlington-transit/","date_added":1271252026,"is_official":1,"dataexchange_id":"arlington-transit","current_datafile":"arlington-transit_20131014_0431","id":7,"createdAt":"2013-10-15T20:51:21.000Z","updatedAt":"2013-10-15T20:51:21.000Z"},{"date_last_updated":1378775635,"feed_baseurl":"http://www.bt4u.org/gtfs/google_transit.zip","name":"Blacksburg Transit","area":"Blacksburk","url":"http://www.btransit.org","country":"United States","state":"Virginia","license_url":"","dataexchange_url":"http://www.gtfs-data-exchange.com/agency/blacksburg-transit/","date_added":1237489325,"is_official":1,"dataexchange_id":"blacksburg-transit","current_datafile":"blacksburg-transit_20130910_0113","id":8,"createdAt":"2013-10-15T20:51:22.000Z","updatedAt":"2013-10-15T20:51:22.000Z"},{"date_last_updated":1372057697,"feed_baseurl":"http://www.broward.org/transitdata/","name":"Broward County Transit","area":"Broward County","url":"http://www.broward.org/bct","country":"United States","state":"Florida","license_url":"","dataexchange_url":"http://www.gtfs-data-exchange.com/agency/broward-county-transit/","date_added":1236828837,"is_official":1,"dataexchange_id":"broward-county-transit","current_datafile":"broward-county-transit_20130624_0708","id":9,"createdAt":"2013-10-15T20:51:22.000Z","updatedAt":"2013-10-15T20:51:22.000Z"},{"date_last_updated":1359000294,"feed_baseurl":"http://trilliumtransit.com/transit_feeds/butte-mt-us/","name":"Butte-Silver Bow","area":"","url":"http://www.buttebus.org/","country":"United States","state":"","license_url":"","dataexchange_url":"http://www.gtfs-data-exchange.com/agency/butte-silver-bow/","date_added":1359000294,"is_official":1,"dataexchange_id":"butte-silver-bow","current_datafile":"butte-silver-bow_20130124_0404","id":10,"createdAt":"2013-10-15T20:51:22.000Z","updatedAt":"2013-10-15T20:51:22.000Z"},{"date_last_updated":1377874379,"feed_baseurl":"http://trilliumtransit.com/transit_feeds/stanislaus-ca-us/","name":"Bus Line Service of Turlock","area":"Turlock","url":"http://www.turlock.ca.us/citydepartments/developmentservices/transitservices/blasttransitlines/","country":"United States","state":"California","license_url":"","dataexchange_url":"http://www.gtfs-data-exchange.com/agency/bus-line-service-of-turlock/","date_added":1287129508,"is_official":1,"dataexchange_id":"bus-line-service-of-turlock","current_datafile":"stanislaus-ca-archiver_20130830_1452","id":11,"createdAt":"2013-10-15T20:51:23.000Z","updatedAt":"2013-10-15T20:51:23.000Z"},{"date_last_updated":1378431092,"feed_baseurl":"http://www.cdta.org/schedules_developer_tools.php","name":"CDTA","area":"Albany","url":"http://www.cdta.org","country":"United States","state":"New York","license_url":"","dataexchange_url":"http://www.gtfs-data-exchange.com/agency/cdta/","date_added":1257787290,"is_official":1,"dataexchange_id":"cdta","current_datafile":"cdta_20130906_0131","id":12,"createdAt":"2013-10-15T20:51:23.000Z","updatedAt":"2013-10-15T20:51:23.000Z"},{"date_last_updated":1289851066,"feed_baseurl":"http://sites.google.com/site/gotrianglegtfs/google-transit/ctran","name":"Cary Transit","area":"","url":"http://www.townofcary.org/Departments/Planning_Department/Transportation/C-Tran.htm","country":"United States","state":"North Carolina","license_url":"","dataexchange_url":"http://www.gtfs-data-exchange.com/agency/cary-transit/","date_added":1289851066,"is_official":1,"dataexchange_id":"cary-transit","current_datafile":"cary-transit_20101115_1957","id":13,"createdAt":"2013-10-15T20:51:24.000Z","updatedAt":"2013-10-15T20:51:24.000Z"},{"date_last_updated":1378256886,"feed_baseurl":"http://oregon-gtfs.com/gtfs_data/caravan-or-us/","name":"Caravan Airport Transportation","area":"","url":"http://www.caravanairporttransportation.com/","country":"United States","state":"Oregon","license_url":"","dataexchange_url":"http://www.gtfs-data-exchange.com/agency/caravan-airport-transportation/","date_added":1285039235,"is_official":1,"dataexchange_id":"caravan-airport-transportation","current_datafile":"caravan-airport-transportation_20130904_0108","id":14,"createdAt":"2013-10-15T20:51:24.000Z","updatedAt":"2013-10-15T20:51:24.000Z"},{"date_last_updated":1319598950,"feed_baseurl":"http://mta.maryland.gov/business/publicgtfsdata.cfm","name":"Central Maryland Regional Transit","area":"Laurel","url":"http://www.corridortransit.com","country":"United States","state":"Maryland","license_url":"","dataexchange_url":"http://www.gtfs-data-exchange.com/agency/central-maryland-regional-transit/","date_added":1285661081,"is_official":1,"dataexchange_id":"central-maryland-regional-transit","current_datafile":"mta-maryland-archiver_20111026_0315","id":15,"createdAt":"2013-10-15T20:51:24.000Z","updatedAt":"2013-10-15T20:51:24.000Z"},{"date_last_updated":1378775511,"feed_baseurl":"http://oregon-gtfs.com/gtfs_data/cascadeseast-or-us/","name":"Cascades East Transit","area":"City of Bend and region","url":"http://www.cascadeseasttransit.com/","country":"United States","state":"Oregon","license_url":"http://oregon-gtfs.com/","dataexchange_url":"http://www.gtfs-data-exchange.com/agency/cascades-east-transit/","date_added":1285039175,"is_official":1,"dataexchange_id":"cascades-east-transit","current_datafile":"cascades-east-transit_20130910_0111","id":16,"createdAt":"2013-10-15T20:51:24.000Z","updatedAt":"2013-10-15T20:51:24.000Z"},{"date_last_updated":1377874379,"feed_baseurl":"http://trilliumtransit.com/transit_feeds/stanislaus-ca-us/","name":"Ceres Area Transit","area":"Ceres","url":"http://www.ci.ceres.ca.us/CeresAreaTransit/CAT.html","country":"United States","state":"California","license_url":"","dataexchange_url":"http://www.gtfs-data-exchange.com/agency/ceres-area-transit/","date_added":1287129508,"is_official":1,"dataexchange_id":"ceres-area-transit","current_datafile":"stanislaus-ca-archiver_20130830_1452","id":17,"createdAt":"2013-10-15T20:51:25.000Z","updatedAt":"2013-10-15T20:51:25.000Z"},{"date_last_updated":1319598950,"feed_baseurl":"http://mta.maryland.gov/business/publicgtfsdata.cfm","name":"Charm City Circulator","area":"Baltimore City","url":"http://www.charmcitycirculator.com","country":"United States","state":"Maryland","license_url":"","dataexchange_url":"http://www.gtfs-data-exchange.com/agency/charm-city-circulator/","date_added":1297654991,"is_official":1,"dataexchange_id":"charm-city-circulator","current_datafile":"mta-maryland-archiver_20111026_0315","id":18,"createdAt":"2013-10-15T20:51:28.000Z","updatedAt":"2013-10-15T20:51:28.000Z"},{"date_last_updated":1361161495,"feed_baseurl":"ftp://ftp.ci.corvallis.or.us/pw/Transportation/GoogleTransitFeed/Google_Transit.zip","name":"City of Albany / Linn Benton Loop","area":"Albany","url":"http://www.cityofalbany.net/publicworks/transit/","country":"United States","state":"Oregon","license_url":"","dataexchange_url":"http://www.gtfs-data-exchange.com/agency/city-of-albany-linn-benton-loop/","date_added":1340089783,"is_official":1,"dataexchange_id":"city-of-albany-linn-benton-loop","current_datafile":"city-of-albany-linn-benton-loop-archiver_20130218_0424","id":19,"createdAt":"2013-10-15T20:51:28.000Z","updatedAt":"2013-10-15T20:51:28.000Z"},{"date_last_updated":1346296007,"feed_baseurl":"http://jump.nextinsight.com/gtfs/ni_citilink/google_transit.zip","name":"Citilink","area":"Fort Wayne","url":"http://www.fwcitilink.com/","country":"United States","state":"Indiana","license_url":"","dataexchange_url":"http://www.gtfs-data-exchange.com/agency/citilink/","date_added":1314673326,"is_official":1,"dataexchange_id":"citilink","current_datafile":"citilink_20120830_0306","id":20,"createdAt":"2013-10-15T20:51:28.000Z","updatedAt":"2013-10-15T20:51:28.000Z"},{"date_last_updated":1358915490,"feed_baseurl":"http://trilliumtransit.com/transit_feeds/corona-ca-us/gtfs.zip","name":"Corona Cruiser","area":"City of Corona","url":"http://www.coronatransit.com","country":"United States","state":"California","license_url":"http://www.discovercorona.com/City-Departments/Public-Works/Transportation/GTFS.aspx","dataexchange_url":"http://www.gtfs-data-exchange.com/agency/corona-cruiser/","date_added":1306205864,"is_official":1,"dataexchange_id":"corona-cruiser","current_datafile":"corona-cruiser_20130123_0431","id":21,"createdAt":"2013-10-15T20:51:28.000Z","updatedAt":"2013-10-15T20:51:28.000Z"},{"date_last_updated":1289851131,"feed_baseurl":"http://sites.google.com/site/gotrianglegtfs/google-transit/data","name":"Durham Area Transit Authority","area":"","url":"http://data.durhamnc.gov/Index_DATA.cfm","country":"United States","state":"North Carolina","license_url":"","dataexchange_url":"http://www.gtfs-data-exchange.com/agency/durham-area-transit-authority/","date_added":1289851131,"is_official":1,"dataexchange_id":"durham-area-transit-authority","current_datafile":"durham-area-transit-authority_20101115_1958","id":22,"createdAt":"2013-10-15T20:51:29.000Z","updatedAt":"2013-10-15T20:51:29.000Z"},{"date_last_updated":1377877040,"feed_baseurl":"http://www.fairfaxcounty.gov/connector/data/connector_gtfs.zip","name":"Fairfax Connector","area":"Fairfax","url":"http://www.fairfaxconnector.com","country":"United States","state":"Virginia","license_url":"","dataexchange_url":"http://www.gtfs-data-exchange.com/agency/fairfax-connector/","date_added":1351740446,"is_official":1,"dataexchange_id":"fairfax-connector","current_datafile":"fairfax-connector_20130830_1537","id":23,"createdAt":"2013-10-15T20:51:29.000Z","updatedAt":"2013-10-15T20:51:29.000Z"},{"date_last_updated":1368156423,"feed_baseurl":"http://trilliumtransit.com/transit_feeds/fairfield-ca-us/","name":"Fairfield and Suisun Transit","area":"Fairfield","url":"http://www.fasttransit.org/","country":"United States","state":"California","license_url":"","dataexchange_url":"http://www.gtfs-data-exchange.com/agency/fairfield-and-suisun-transit/","date_added":1259971474,"is_official":1,"dataexchange_id":"fairfield-and-suisun-transit","current_datafile":"fairfield-and-suisun-transit_20130510_0327","id":24,"createdAt":"2013-10-15T20:51:29.000Z","updatedAt":"2013-10-15T20:51:29.000Z"},{"date_last_updated":1378949743,"feed_baseurl":"http://trilliumtransit.com/transit_feeds/humboldtcounty-ca-us/","name":"Eureka Transit Service","area":"Humboldt County","url":"http://www.eurekatransit.org/","country":"United States","state":"California","license_url":"","dataexchange_url":"http://www.gtfs-data-exchange.com/agency/eureka-transit-service/","date_added":1225261819,"is_official":1,"dataexchange_id":"eureka-transit-service","current_datafile":"humboldt-archiver_20130912_0135","id":25,"createdAt":"2013-10-15T20:51:29.000Z","updatedAt":"2013-10-15T20:51:29.000Z"},{"date_last_updated":1359643210,"feed_baseurl":"","name":"Hillsborough Area Regional Transit","area":"Tampa","url":"http://www.gohart.org","country":"United States","state":"Florida","license_url":"","dataexchange_url":"http://www.gtfs-data-exchange.com/agency/hillsborough-area-regional-transit/","date_added":1310389213,"is_official":1,"dataexchange_id":"hillsborough-area-regional-transit","current_datafile":"hillsborough-area-regional-transit_20130131_1440","id":30,"createdAt":"2013-10-15T20:51:30.000Z","updatedAt":"2013-10-15T20:51:30.000Z"},{"date_last_updated":1374695602,"feed_baseurl":"http://www.gtfs-data-exchange.com/agency/jefferson-transit-authority/","name":"Jefferson Transit Authority","area":"Port Townsend","url":"http://www.jeffersontransit.com/","country":"United States","state":"Washington","license_url":"http://www.jeffersontransit.com/information.html","dataexchange_url":"http://www.gtfs-data-exchange.com/agency/jefferson-transit-authority/","date_added":1231484629,"is_official":1,"dataexchange_id":"jefferson-transit-authority","current_datafile":"jefferson-transit-authority_20130724_1953","id":35,"createdAt":"2013-10-15T20:51:31.000Z","updatedAt":"2013-10-15T20:51:31.000Z"},{"date_last_updated":1320984818,"feed_baseurl":"http://www.masontransit.org/gtfs/","name":"Mason Transit","area":"","url":"http://www.masontransit.org/","country":"United States","state":"Washington","license_url":"","dataexchange_url":"http://www.gtfs-data-exchange.com/agency/mason-transit/","date_added":1306739047,"is_official":1,"dataexchange_id":"mason-transit","current_datafile":"mason-transit_20111111_0413","id":37,"createdAt":"2013-10-15T20:51:35.000Z","updatedAt":"2013-10-15T20:51:35.000Z"},{"date_last_updated":1369537613,"feed_baseurl":"http://www.eot.state.ma.us/developers","name":"Merrimack Valley Regional Transit Authority","area":"","url":"http://www.mvrta.com","country":"United States","state":"Massachusetts","license_url":"","dataexchange_url":"http://www.gtfs-data-exchange.com/agency/merrimack-valley-regional-transit-authority/","date_added":1249438987,"is_official":1,"dataexchange_id":"merrimack-valley-regional-transit-authority","current_datafile":"merrimack-valley-regional-transit-authority_20130526_0306","id":39,"createdAt":"2013-10-15T20:51:36.000Z","updatedAt":"2013-10-15T20:51:36.000Z"},{"date_last_updated":1278422722,"feed_baseurl":"","name":"Mountain Metropolitan Transit","area":"Colorado Springs","url":"http://www.mmtransit.com","country":"United States","state":"Colorado","license_url":"","dataexchange_url":"http://www.gtfs-data-exchange.com/agency/mountain-metropolitan-transit/","date_added":1278422722,"is_official":1,"dataexchange_id":"mountain-metropolitan-transit","current_datafile":"mountain-metropolitan-transit_20100706_1325","id":47,"createdAt":"2013-10-15T20:51:38.000Z","updatedAt":"2013-10-15T20:51:38.000Z"},{"date_last_updated":1367845157,"feed_baseurl":"http://www.njtransit.com/developer","name":"New Jersey Transit","area":"","url":"http://www.njtransit.com/sf/sf_servlet.srv?hdnPageAction=TripPlannerTo","country":"United States","state":"New Jersey","license_url":"","dataexchange_url":"http://www.gtfs-data-exchange.com/agency/new-jersey-transit/","date_added":1224261936,"is_official":1,"dataexchange_id":"new-jersey-transit","current_datafile":"kentonfalana_20130506_1259","id":50,"createdAt":"2013-10-15T20:51:40.000Z","updatedAt":"2013-10-15T20:51:40.000Z"},{"date_last_updated":1366168348,"feed_baseurl":"http://www.trilliumtransit.com/transit_feeds/riovista-ca-us/","name":"Rio Vista Delta Breeze","area":"Rio Vista","url":"http://www.rio-vista-ca.com/transit/","country":"United States","state":"California","license_url":"","dataexchange_url":"http://www.gtfs-data-exchange.com/agency/rio-vista-delta-breeze/","date_added":1225294699,"is_official":1,"dataexchange_id":"rio-vista-delta-breeze","current_datafile":"rio-vista-delta-breeze_20130417_0312","id":58,"createdAt":"2013-10-15T20:51:41.000Z","updatedAt":"2013-10-15T20:51:41.000Z"},{"date_last_updated":1377876534,"feed_baseurl":"http://iportal.sacrt.com/GTFS/SRTD","name":"Sacramento Regional Transit","area":"Sacramento","url":"http://www.sacrt.com","country":"United States","state":"California","license_url":"http://www.sacrt.com/gtfs.stm","dataexchange_url":"http://www.gtfs-data-exchange.com/agency/sacramento-regional-transit/","date_added":1225294237,"is_official":1,"dataexchange_id":"sacramento-regional-transit","current_datafile":"sacramento-regional-transit_20130830_1528","id":62,"createdAt":"2013-10-15T20:51:43.000Z","updatedAt":"2013-10-15T20:51:43.000Z"},{"date_last_updated":1366513665,"feed_baseurl":"http://trilliumtransit.com/transit_feeds/spacecoast-fl-us/","name":"Space Coast Area Transit","area":"Brevard County","url":"http://www.ridescat.com/","country":"United States","state":"Florida","license_url":"","dataexchange_url":"http://www.gtfs-data-exchange.com/agency/space-coast-area-transit/","date_added":1285694678,"is_official":1,"dataexchange_id":"space-coast-area-transit","current_datafile":"space-coast-area-transit_20130421_0307","id":66,"createdAt":"2013-10-15T20:51:44.000Z","updatedAt":"2013-10-15T20:51:44.000Z"},{"date_last_updated":1362197083,"feed_baseurl":"http://trilliumtransit.com/transit_feeds/tehama-ca-us/","name":"Tehama Rural Area Express","area":"Tehama County","url":"http://www.taketrax.com/","country":"United States","state":"California","license_url":"","dataexchange_url":"http://www.gtfs-data-exchange.com/agency/tehama-rural-area-express/","date_added":1273678979,"is_official":1,"dataexchange_id":"tehama-rural-area-express","current_datafile":"tehama-archiver_20130302_0404","id":71,"createdAt":"2013-10-15T20:51:45.000Z","updatedAt":"2013-10-15T20:51:45.000Z"},{"date_last_updated":1371871139,"feed_baseurl":"http://trilliumtransit.com/transit_feeds/escalon-ca-us/","name":"eTrans","area":"","url":"http://www.cityofescalon.org/transit.htm","country":"United States","state":"California","license_url":"","dataexchange_url":"http://www.gtfs-data-exchange.com/agency/etrans/","date_added":1273678797,"is_official":1,"dataexchange_id":"etrans","current_datafile":"etrans_20130622_0318","id":83,"createdAt":"2013-10-15T20:51:46.000Z","updatedAt":"2013-10-15T20:51:46.000Z"},{"date_last_updated":1319598950,"feed_baseurl":"http://mta.maryland.gov/business/publicgtfsdata.cfm","name":"Frederick Transit Meet-The-MARC","area":"","url":"http://www.frederickcountymd.gov/index.asp?NID=207","country":"United States","state":"Maryland","license_url":"","dataexchange_url":"http://www.gtfs-data-exchange.com/agency/frederick-transit-meet-the-marc/","date_added":1297654991,"is_official":1,"dataexchange_id":"frederick-transit-meet-the-marc","current_datafile":"mta-maryland-archiver_20111026_0315","id":26,"createdAt":"2013-10-15T20:51:30.000Z","updatedAt":"2013-10-15T20:51:30.000Z"},{"date_last_updated":1364786040,"feed_baseurl":"http://www.riderta.com/gtfs/latest","name":"Greater Cleveland Regional Transit Authority","area":"Cleveland","url":"http://www.riderta.com/","country":"United States","state":"Ohio","license_url":"","dataexchange_url":"http://www.gtfs-data-exchange.com/agency/greater-cleveland-regional-transit-authority/","date_added":1257792041,"is_official":1,"dataexchange_id":"greater-cleveland-regional-transit-authority","current_datafile":"greater-cleveland-regional-transit-authority_20130401_0314","id":29,"createdAt":"2013-10-15T20:51:30.000Z","updatedAt":"2013-10-15T20:51:30.000Z"},{"date_last_updated":1361334758,"feed_baseurl":"http://www.gtfs-data-exchange.com/agency/island-transit/","name":"Island Transit","area":"Island County","url":"http://www.islandtransit.org/","country":"United States","state":"Washington","license_url":"http://islandtransit.org/license_agreement/","dataexchange_url":"http://www.gtfs-data-exchange.com/agency/island-transit/","date_added":1232046701,"is_official":1,"dataexchange_id":"island-transit","current_datafile":"island-transit_20130220_0432","id":34,"createdAt":"2013-10-15T20:51:31.000Z","updatedAt":"2013-10-15T20:51:31.000Z"},{"date_last_updated":1346696730,"feed_baseurl":"http://www.mountainline.com/files/google_transit.zip","name":"Mountain Line (MUTD)","area":"Missoula","url":"http://www.mountainline.com","country":"United States","state":"Montana","license_url":"","dataexchange_url":"http://www.gtfs-data-exchange.com/agency/mountain-line-mutd/","date_added":1346696730,"is_official":1,"dataexchange_id":"mountain-line-mutd","current_datafile":"mountain-line-mutd_20120903_1825","id":46,"createdAt":"2013-10-15T20:51:38.000Z","updatedAt":"2013-10-15T20:51:38.000Z"},{"date_last_updated":1369364838,"feed_baseurl":"http://www.psta.net/latest/google_transit.zip","name":"PSTA","area":"","url":"http://www.psta.net","country":"United States","state":"Florida","license_url":"","dataexchange_url":"http://www.gtfs-data-exchange.com/agency/psta/","date_added":1320091332,"is_official":1,"dataexchange_id":"psta","current_datafile":"psta_20130524_0307","id":52,"createdAt":"2013-10-15T20:51:41.000Z","updatedAt":"2013-10-15T20:51:41.000Z"},{"date_last_updated":1305169248,"feed_baseurl":"http://www.panynj.gov/path/developers.html","name":"Port Authority of New York & New Jersey","area":"Newark/New York City","url":"http://www.panynj.gov/path/","country":"United States","state":"New Jersey","license_url":"","dataexchange_url":"http://www.gtfs-data-exchange.com/agency/port-authority-of-new-york-new-jersey/","date_added":1305169248,"is_official":1,"dataexchange_id":"port-authority-of-new-york-new-jersey","current_datafile":"port-authority-of-new-york-new-jersey_20110512_0300","id":55,"createdAt":"2013-10-15T20:51:41.000Z","updatedAt":"2013-10-15T20:51:41.000Z"},{"date_last_updated":1329357502,"feed_baseurl":"http://oregon-gtfs.com/gtfs_data/rideconnection-or-us","name":"Ride Connection","area":"Portland Metro Area","url":"http://www.rideconnection.org","country":"United States","state":"Oregon","license_url":"http://www.rideconnection.org/ride/AboutUs/GTFSLicensingAgreement.aspx","dataexchange_url":"http://www.gtfs-data-exchange.com/agency/ride-connection/","date_added":1329357502,"is_official":1,"dataexchange_id":"ride-connection","current_datafile":"ride-connection_20120216_0158","id":57,"createdAt":"2013-10-15T20:51:41.000Z","updatedAt":"2013-10-15T20:51:41.000Z"},{"date_last_updated":1377876346,"feed_baseurl":"http://www.rtd-denver.com/GoogleFeeder/","name":"Regional Transportation District","area":"Denver","url":"http://rtd-denver.com","country":"United States","state":"Colorado","license_url":"http://www.rtd-denver.com/License_Agreement/License_Agreement.pdf","dataexchange_url":"http://www.gtfs-data-exchange.com/agency/regional-transportation-district/","date_added":1225263454,"is_official":1,"dataexchange_id":"regional-transportation-district","current_datafile":"regional-transportation-district_20130830_1525","id":60,"createdAt":"2013-10-15T20:51:43.000Z","updatedAt":"2013-10-15T20:51:43.000Z"},{"date_last_updated":1378430961,"feed_baseurl":"https://sites.google.com/site/slocountytransit/google-transit-docs/slorta_datafiles/latest/google_transit.zip","name":"San Luis Obispo Regional Transit Authority","area":"San Luis Obispo County","url":"http://www.slorta.org","country":"United States","state":"California","license_url":"","dataexchange_url":"http://www.gtfs-data-exchange.com/agency/san-luis-obispo-regional-transit-authority/","date_added":1303267157,"is_official":1,"dataexchange_id":"san-luis-obispo-regional-transit-authority","current_datafile":"san-luis-obispo-regional-transit-authority_20130906_0129","id":64,"createdAt":"2013-10-15T20:51:43.000Z","updatedAt":"2013-10-15T20:51:43.000Z"},{"date_last_updated":1376520079,"feed_baseurl":"","name":"Spokane Transit Authority","area":"Spokane","url":"http://www.spokanetransit.com","country":"United States","state":"Washington","license_url":"","dataexchange_url":"http://www.gtfs-data-exchange.com/agency/spokane-transit-authority/","date_added":1292403428,"is_official":1,"dataexchange_id":"spokane-transit-authority","current_datafile":"spokane-transit-authority_20130814_2241","id":67,"createdAt":"2013-10-15T20:51:44.000Z","updatedAt":"2013-10-15T20:51:44.000Z"},{"date_last_updated":1377874379,"feed_baseurl":"","name":"Stanislaus Regional Transit","area":"Stanislaus County","url":"http://www.srt.org/","country":"United States","state":"California","license_url":"","dataexchange_url":"http://www.gtfs-data-exchange.com/agency/stanislaus-regional-transit/","date_added":1287129507,"is_official":1,"dataexchange_id":"stanislaus-regional-transit","current_datafile":"stanislaus-ca-archiver_20130830_1452","id":69,"createdAt":"2013-10-15T20:51:45.000Z","updatedAt":"2013-10-15T20:51:45.000Z"},{"date_last_updated":1351290857,"feed_baseurl":"","name":"Topeka Metro","area":"Topeka","url":"http://www.topekametro.org","country":"United States","state":"Kansas","license_url":"","dataexchange_url":"http://www.gtfs-data-exchange.com/agency/topeka-metro/","date_added":1351290857,"is_official":1,"dataexchange_id":"topeka-metro","current_datafile":"topeka-metro_20121026_2234","id":73,"createdAt":"2013-10-15T20:51:45.000Z","updatedAt":"2013-10-15T20:51:45.000Z"},{"date_last_updated":1289851436,"feed_baseurl":"http://sites.google.com/site/gotrianglegtfs/google-transit/tta","name":"Triangle Transit","area":"","url":"http://www.triangletransit.org","country":"United States","state":"North Carolina","license_url":"","dataexchange_url":"http://www.gtfs-data-exchange.com/agency/triangle-transit/","date_added":1289851254,"is_official":1,"dataexchange_id":"triangle-transit","current_datafile":"triangle-transit_20101115_2003","id":75,"createdAt":"2013-10-15T20:51:45.000Z","updatedAt":"2013-10-15T20:51:45.000Z"},{"date_last_updated":1377897688,"feed_baseurl":"","name":"Yakima Transit","area":"Yakima","url":"http://www.yakimatransit.org","country":"United States","state":"Washington","license_url":"","dataexchange_url":"http://www.gtfs-data-exchange.com/agency/yakima-transit/","date_added":1327299339,"is_official":1,"dataexchange_id":"yakima-transit","current_datafile":"yakima-transit_20130830_2121","id":81,"createdAt":"2013-10-15T20:51:46.000Z","updatedAt":"2013-10-15T20:51:46.000Z"},{"date_last_updated":1377873948,"feed_baseurl":"http://www.wmata.com/rider_tools/developer_resources.cfm","name":"Washington Metropolitan Area Transit Authority","area":"","url":"http://www.wmata.com","country":"United States","state":"Washington DC","license_url":"http://www.wmata.com/rider_tools/license_agreement.cfm","dataexchange_url":"http://www.gtfs-data-exchange.com/agency/wmata/","date_added":1237835874,"is_official":1,"dataexchange_id":"wmata","current_datafile":"mvta-archiver_20130830_1445","id":84,"createdAt":"2013-10-15T20:51:48.000Z","updatedAt":"2013-10-15T20:51:48.000Z"},{"date_last_updated":1325748563,"feed_baseurl":"http://oregon-gtfs.com/gtfs_data/hut-or-us/","name":"HUT Airport Shuttle","area":"","url":"http://www.portlandairportshuttle.com/","country":"United States","state":"Oregon","license_url":"","dataexchange_url":"http://www.gtfs-data-exchange.com/agency/hut-airport-shuttle/","date_added":1285039114,"is_official":1,"dataexchange_id":"hut-airport-shuttle","current_datafile":"hut-airport-shuttle_20120105_0729","id":27,"createdAt":"2013-10-15T20:51:30.000Z","updatedAt":"2013-10-15T20:51:30.000Z"},{"date_last_updated":1262101635,"feed_baseurl":"http://irvineshuttle.net/files/managed/Document/70/google_transit.zip","name":"Irvine Shuttle","area":"Irvine","url":"http://www.irvineshuttle.net","country":"United States","state":"California","license_url":"http://www.cityofirvine.org/civica/filebank/blobdload.asp?BlobID=12803","dataexchange_url":"http://www.gtfs-data-exchange.com/agency/irvine-shuttle/","date_added":1236231257,"is_official":1,"dataexchange_id":"irvine-shuttle","current_datafile":"irvine-shuttle_20091229_1547","id":32,"createdAt":"2013-10-15T20:51:31.000Z","updatedAt":"2013-10-15T20:51:31.000Z"},{"date_last_updated":1378430410,"feed_baseurl":"http://www.itsmarta.com/marta-developer-resources.aspx","name":"Metropolitan Atlanta Rapid Transit Authority","area":"Atlanta","url":"http://www.itsmarta.com","country":"United States","state":"Georgia","license_url":"","dataexchange_url":"http://www.gtfs-data-exchange.com/agency/metropolitan-atlanta-rapid-transit-authority/","date_added":1350680993,"is_official":1,"dataexchange_id":"metropolitan-atlanta-rapid-transit-authority","current_datafile":"metropolitan-atlanta-rapid-transit-authority_20130906_0120","id":41,"createdAt":"2013-10-15T20:51:37.000Z","updatedAt":"2013-10-15T20:51:37.000Z"},{"date_last_updated":1377873886,"feed_baseurl":"http://www.miamidade.gov/transit/googletransit/current/google_transit.zip","name":"Miami Dade Transit","area":"Miami-Dade","url":"http://www.miamidade.gov/transit","country":"United States","state":"Florida","license_url":"","dataexchange_url":"http://www.gtfs-data-exchange.com/agency/miami-dade-transit/","date_added":1282588726,"is_official":1,"dataexchange_id":"miami-dade-transit","current_datafile":"miami-dade-transit_20130830_1444","id":44,"createdAt":"2013-10-15T20:51:38.000Z","updatedAt":"2013-10-15T20:51:38.000Z"},{"date_last_updated":1370576347,"feed_baseurl":"http://trilliumtransit.com/transit_feeds/naipta-az-us/","name":"Mountain Line","area":"Flagstaff","url":"http://www.mountainline.az.gov/","country":"United States","state":"Arizona","license_url":"","dataexchange_url":"http://www.gtfs-data-exchange.com/agency/mountain-line/","date_added":1233899771,"is_official":1,"dataexchange_id":"mountain-line","current_datafile":"mountain-line_20130607_0339","id":48,"createdAt":"2013-10-15T20:51:38.000Z","updatedAt":"2013-10-15T20:51:38.000Z"},{"date_last_updated":1379556259,"feed_baseurl":"http://www.eot.state.ma.us/developers/","name":"PVTA","area":"Pioneer Valley","url":"http://www.pvta.com","country":"United States","state":"Massachusetts","license_url":"","dataexchange_url":"http://www.gtfs-data-exchange.com/agency/pvta/","date_added":1252642701,"is_official":1,"dataexchange_id":"pvta","current_datafile":"pvta_20130919_0204","id":56,"createdAt":"2013-10-15T20:51:41.000Z","updatedAt":"2013-10-15T20:51:41.000Z"},{"date_last_updated":1379466299,"feed_baseurl":"http://scmtd.com/google_transit/google_transit.zip","name":"Santa Cruz Metro","area":"Santa Cruz","url":"http://www.scmtd.com","country":"United States","state":"California","license_url":"","dataexchange_url":"http://www.gtfs-data-exchange.com/agency/santa-cruz-metro/","date_added":1320092606,"is_official":1,"dataexchange_id":"santa-cruz-metro","current_datafile":"santa-cruz-metro_20130918_0104","id":63,"createdAt":"2013-10-15T20:51:43.000Z","updatedAt":"2013-10-15T20:51:43.000Z"},{"date_last_updated":1377879160,"feed_baseurl":"http://oregon-gtfs.com/gtfs_data/southwestpoint-or-us/","name":"The Shuttle, Inc.","area":"","url":"http://www.southwest-point.com/","country":"United States","state":"Oregon","license_url":"","dataexchange_url":"http://www.gtfs-data-exchange.com/agency/the-shuttle-inc/","date_added":1273679041,"is_official":1,"dataexchange_id":"the-shuttle-inc","current_datafile":"the-shuttle-inc_20130830_1612","id":72,"createdAt":"2013-10-15T20:51:45.000Z","updatedAt":"2013-10-15T20:51:45.000Z"},{"date_last_updated":1345433035,"feed_baseurl":"http://trilliumtransit.com/transit_feeds/tillamook-or-us/","name":"Tillamook County Transportation District","area":"Tillamook County","url":"http://www.tillamookbus.com/","country":"United States","state":"Oregon","license_url":"","dataexchange_url":"http://www.gtfs-data-exchange.com/agency/tillamook-county-transportation-district/","date_added":1247713114,"is_official":1,"dataexchange_id":"tillamook-county-transportation-district","current_datafile":"tillamook-county-transportation-district_20120820_0323","id":74,"createdAt":"2013-10-15T20:51:45.000Z","updatedAt":"2013-10-15T20:51:45.000Z"},{"date_last_updated":1374030193,"feed_baseurl":"http://www.trilliumtransit.com/transit_feeds/trinity-ca-us/","name":"Trinity Transit","area":"Trinity County","url":"http://trinitytransit.org/","country":"United States","state":"California","license_url":"http://www.trinitytransit.org/gtfs/","dataexchange_url":"http://www.gtfs-data-exchange.com/agency/trinity-transit/","date_added":1259791498,"is_official":1,"dataexchange_id":"trinity-transit","current_datafile":"trinity-transit_20130717_0303","id":77,"createdAt":"2013-10-15T20:51:45.000Z","updatedAt":"2013-10-15T20:51:45.000Z"},{"date_last_updated":1374210192,"feed_baseurl":"http://www.wstip.org/google/valley/latest/google_transit.zip","name":"Valley Transit","area":"Walla Walla","url":"http://www.valleytransit.com/","country":"United States","state":"Washington","license_url":"","dataexchange_url":"http://www.gtfs-data-exchange.com/agency/valley-transit/","date_added":1256689996,"is_official":1,"dataexchange_id":"valley-transit","current_datafile":"valley-transit_20130719_0503","id":79,"createdAt":"2013-10-15T20:51:46.000Z","updatedAt":"2013-10-15T20:51:46.000Z"},{"date_last_updated":1377876789,"feed_baseurl":"http://googletf.gohrt.com/","name":"Hampton Roads Transit (HRT)","area":"Hampton Roads","url":"http://www.gohrt.com/","country":"United States","state":"Virginia","license_url":"","dataexchange_url":"http://www.gtfs-data-exchange.com/agency/hampton-roads-transit-hrt/","date_added":1228459907,"is_official":1,"dataexchange_id":"hampton-roads-transit-hrt","current_datafile":"hampton-roads-transit-hrt_20130830_1533","id":28,"createdAt":"2013-10-15T20:51:30.000Z","updatedAt":"2013-10-15T20:51:30.000Z"},{"date_last_updated":1378948399,"feed_baseurl":"http://www.intercitytransit.com/googledata/google_transit.zip","name":"Intercity Transit","area":"Olympia","url":"http://www.Intercitytransit.com","country":"United States","state":"Washington","license_url":"","dataexchange_url":"http://www.gtfs-data-exchange.com/agency/intercity-transit/","date_added":1319081005,"is_official":1,"dataexchange_id":"intercity-transit","current_datafile":"intercity-transit_20130912_0113","id":33,"createdAt":"2013-10-15T20:51:31.000Z","updatedAt":"2013-10-15T20:51:31.000Z"},{"date_last_updated":1377873948,"feed_baseurl":"http://www.datafinder.org/metadata/mvtaschedule.htm","name":"MVTA","area":"","url":"http://www.mvta.com","country":"United States","state":"Minnesota","license_url":"","dataexchange_url":"http://www.gtfs-data-exchange.com/agency/mvta/","date_added":1298518473,"is_official":1,"dataexchange_id":"mvta","current_datafile":"mvta-archiver_20130830_1445","id":36,"createdAt":"2013-10-15T20:51:35.000Z","updatedAt":"2013-10-15T20:51:35.000Z"},{"date_last_updated":1328329165,"feed_baseurl":"http://www.metrolinktrains.com/tripplanner/schedule_data.php","name":"Metrolink","area":"","url":"http://www.metrolinktrains.com","country":"United States","state":"California","license_url":"http://www.metrolinktrains.com/tripplanner/license_agreement.php","dataexchange_url":"http://www.gtfs-data-exchange.com/agency/metrolink/","date_added":1225264016,"is_official":1,"dataexchange_id":"metrolink","current_datafile":"metrolink_20120204_0419","id":42,"createdAt":"2013-10-15T20:51:37.000Z","updatedAt":"2013-10-15T20:51:37.000Z"},{"date_last_updated":1279851413,"feed_baseurl":"http://www.montanatransit.com/googletransit/MUTD/","name":"Montana Transit - Mountain Line","area":"Missoula","url":"http://www.mountainline.com","country":"United States","state":"Montana","license_url":"","dataexchange_url":"http://www.gtfs-data-exchange.com/agency/montana-transit-mountain-line/","date_added":1257831590,"is_official":1,"dataexchange_id":"montana-transit-mountain-line","current_datafile":"montana-transit-mountain-line_20100723_0216","id":45,"createdAt":"2013-10-15T20:51:38.000Z","updatedAt":"2013-10-15T20:51:38.000Z"},{"date_last_updated":1367845156,"feed_baseurl":"","name":"NJ Bus","area":"","url":"http://www.njtransit.com/sf/sf_servlet.srv?hdnPageAction=TripPlannerTo","country":"United States","state":"New Jersey","license_url":"","dataexchange_url":"http://www.gtfs-data-exchange.com/agency/nj-bus/","date_added":1228967799,"is_official":1,"dataexchange_id":"nj-bus","current_datafile":"kentonfalana_20130506_1259","id":49,"createdAt":"2013-10-15T20:51:39.000Z","updatedAt":"2013-10-15T20:51:39.000Z"},{"date_last_updated":1370575156,"feed_baseurl":"http://www.octa.net/current/google_transit.zip","name":"Orange County Transportation Authority","area":"Orange County","url":"http://www.octa.net","country":"United States","state":"California","license_url":"http://www.octa.net/disclaimer.aspx","dataexchange_url":"http://www.gtfs-data-exchange.com/agency/orange-county-transportation-authority/","date_added":1225264016,"is_official":1,"dataexchange_id":"orange-county-transportation-authority","current_datafile":"orange-county-transportation-authority_20130607_0319","id":54,"createdAt":"2013-10-15T20:51:41.000Z","updatedAt":"2013-10-15T20:51:41.000Z"},{"date_last_updated":1377875263,"feed_baseurl":"http://sanjoaquinrtd.com/RTD-GTFS/RTD-GTFS.zip","name":"San Joaquin Regional Transit District (RTD)","area":"Stockton","url":"http://sanjoaquinrtd.com","country":"United States","state":"California","license_url":"http://sanjoaquinrtd.com/legal/default.php","dataexchange_url":"http://www.gtfs-data-exchange.com/agency/san-joaquin-regional-transit-district-rtd/","date_added":1297987040,"is_official":1,"dataexchange_id":"san-joaquin-regional-transit-district-rtd","current_datafile":"san-joaquin-regional-transit-district-rtd_20130830_1507","id":61,"createdAt":"2013-10-15T20:51:43.000Z","updatedAt":"2013-10-15T20:51:43.000Z"},{"date_last_updated":1377879532,"feed_baseurl":"http://www.ridethebus.org/Google_Transit/","name":"Sunset Empire Transportation District","area":"Clatsop County","url":"http://www.ridethebus.org/","country":"United States","state":"Oregon","license_url":"","dataexchange_url":"http://www.gtfs-data-exchange.com/agency/sunset-empire-transportation-district/","date_added":1260948559,"is_official":1,"dataexchange_id":"sunset-empire-transportation-district","current_datafile":"sunset-empire-transportation-district_20130830_1618","id":70,"createdAt":"2013-10-15T20:51:45.000Z","updatedAt":"2013-10-15T20:51:45.000Z"},{"date_last_updated":1377878462,"feed_baseurl":"http://www.viainfo.net/BusService/google_transit.zip","name":"VIA Metropolitan Transit","area":"San Antonio","url":"http://www.viainfo.net","country":"United States","state":"Texas","license_url":"http://www.viainfo.net/Opportunities/DevLicense.aspx","dataexchange_url":"http://www.gtfs-data-exchange.com/agency/via-metropolitan-transit/","date_added":1319575419,"is_official":1,"dataexchange_id":"via-metropolitan-transit","current_datafile":"via-metropolitan-transit_20130830_1601","id":78,"createdAt":"2013-10-15T20:51:46.000Z","updatedAt":"2013-10-15T20:51:46.000Z"},{"date_last_updated":1319598950,"feed_baseurl":"http://mta.maryland.gov/business/publicgtfsdata.cfm","name":"Howard Transit","area":"Howard County","url":"http://www.howardtransit.com","country":"United States","state":"Maryland","license_url":"","dataexchange_url":"http://www.gtfs-data-exchange.com/agency/howard-transit/","date_added":1285661081,"is_official":1,"dataexchange_id":"howard-transit","current_datafile":"mta-maryland-archiver_20111026_0315","id":31,"createdAt":"2013-10-15T20:51:31.000Z","updatedAt":"2013-10-15T20:51:31.000Z"},{"date_last_updated":1299123924,"feed_baseurl":"http://www.menlopark.org/departments/trn/google/google_transit.zip","name":"Menlo Park Midday Shuttle","area":"Menlo Park","url":"http://www.menlopark.org/departments/trn/shuttles.html","country":"United States","state":"California","license_url":"","dataexchange_url":"http://www.gtfs-data-exchange.com/agency/menlo-park-midday-shuttle/","date_added":1256689931,"is_official":1,"dataexchange_id":"menlo-park-midday-shuttle","current_datafile":"menlo-park-midday-shuttle_20110303_0345","id":38,"createdAt":"2013-10-15T20:51:35.000Z","updatedAt":"2013-10-15T20:51:35.000Z"},{"date_last_updated":1379466601,"feed_baseurl":"http://www.mta.info/developers/","name":"Long Island Rail Road","area":"Long Island","url":"http://mta.info/lirr","country":"United States","state":"New York","license_url":"","dataexchange_url":"http://www.gtfs-data-exchange.com/agency/long-island-rail-road/","date_added":1263414774,"is_official":1,"dataexchange_id":"long-island-rail-road","current_datafile":"long-island-rail-road_20130918_0110","id":40,"createdAt":"2013-10-15T20:51:36.000Z","updatedAt":"2013-10-15T20:51:36.000Z"},{"date_last_updated":1378775382,"feed_baseurl":"http://ridemetro.org/AboutUs/Publications/DataFiles/google_transit.zip","name":"Metropolitan Transit Authority of Harris County","area":"Houston","url":"http://www.ridemetro.org","country":"United States","state":"Texas","license_url":"http://ridemetro.org/AboutUs/Publications/DataDownloads.aspx","dataexchange_url":"http://www.gtfs-data-exchange.com/agency/metropolitan-transit-authority-of-harris-county/","date_added":1235023129,"is_official":1,"dataexchange_id":"metropolitan-transit-authority-of-harris-county","current_datafile":"metropolitan-transit-authority-of-harris-county_20130910_0109","id":43,"createdAt":"2013-10-15T20:51:37.000Z","updatedAt":"2013-10-15T20:51:37.000Z"},{"date_last_updated":1378256520,"feed_baseurl":"http://www.nfta.com/metro/developers.asp","name":"NFTA-METRO","area":"Buffalo","url":"http://www.nfta.com","country":"United States","state":"New York","license_url":"","dataexchange_url":"http://www.gtfs-data-exchange.com/agency/nfta-metro/","date_added":1263612505,"is_official":1,"dataexchange_id":"nfta-metro","current_datafile":"nfta-metro_20130904_0102","id":51,"createdAt":"2013-10-15T20:51:40.000Z","updatedAt":"2013-10-15T20:51:40.000Z"},{"date_last_updated":1312346908,"feed_baseurl":"http://trilliumtransit.com/transit_feeds/peoplemover-or-us/","name":"People Mover","area":"","url":"http://www.solwest.org/bus_sched.htm","country":"United States","state":"Oregon","license_url":"","dataexchange_url":"http://www.gtfs-data-exchange.com/agency/people-mover/","date_added":1285039053,"is_official":1,"dataexchange_id":"people-mover","current_datafile":"people-mover_20110803_0448","id":53,"createdAt":"2013-10-15T20:51:41.000Z","updatedAt":"2013-10-15T20:51:41.000Z"},{"date_last_updated":1378949743,"feed_baseurl":"http://trilliumtransit.com/transit_feeds/humboldtcounty-ca-us/","name":"Redwood Transit System","area":"Humboldt County","url":"http://www.redwoodtransit.org/","country":"United States","state":"California","license_url":"","dataexchange_url":"http://www.gtfs-data-exchange.com/agency/redwood-transit-system/","date_added":1225261819,"is_official":1,"dataexchange_id":"redwood-transit-system","current_datafile":"humboldt-archiver_20130912_0135","id":59,"createdAt":"2013-10-15T20:51:42.000Z","updatedAt":"2013-10-15T20:51:42.000Z"},{"date_last_updated":1379122063,"feed_baseurl":"http://trilliumtransit.com/transit_feeds/wilsonville-or-us/","name":"South Metro Area Regional Transit","area":"Wilsonville","url":"http://www.ridesmart.com/","country":"United States","state":"Oregon","license_url":"","dataexchange_url":"http://www.gtfs-data-exchange.com/agency/south-metro-area-regional-transit/","date_added":1299729212,"is_official":1,"dataexchange_id":"south-metro-area-regional-transit","current_datafile":"south-metro-area-regional-transit_20130914_0127","id":65,"createdAt":"2013-10-15T20:51:43.000Z","updatedAt":"2013-10-15T20:51:43.000Z"},{"date_last_updated":1362197083,"feed_baseurl":"http://trilliumtransit.com/transit_feeds/tehama-ca-us/","name":"Susanville Indian Rancheria Public Transportation Program","area":"Susanville","url":"http://www.transitunlimited.org/Susanville_Indian_Rancheria_Public_Transportation_Program","country":"United States","state":"California","license_url":"","dataexchange_url":"http://www.gtfs-data-exchange.com/agency/susanville-indian-rancheria-public-transportation-program/","date_added":1273678979,"is_official":1,"dataexchange_id":"susanville-indian-rancheria-public-transportation-program","current_datafile":"tehama-archiver_20130302_0404","id":68,"createdAt":"2013-10-15T20:51:45.000Z","updatedAt":"2013-10-15T20:51:45.000Z"},{"date_last_updated":1370056197,"feed_baseurl":"http://oregon-gtfs.com/gtfs_data/umpquatransit-or-us/","name":"U-Trans","area":"Roseburg","url":"http://www.umpquatransit.com/","country":"United States","state":"Oregon","license_url":"","dataexchange_url":"http://www.gtfs-data-exchange.com/agency/u-trans/","date_added":1305168945,"is_official":1,"dataexchange_id":"u-trans","current_datafile":"u-trans_20130601_0309","id":76,"createdAt":"2013-10-15T20:51:45.000Z","updatedAt":"2013-10-15T20:51:45.000Z"},{"date_last_updated":1371870652,"feed_baseurl":"http://oregon-gtfs.com/gtfs_data/woodburn-or-us/","name":"Woodburn Transit","area":"Woodburn","url":"http://www.woodburn-or.gov/publicworks/transit.aspx","country":"United States","state":"Oregon","license_url":"http://oregon-gtfs.com/","dataexchange_url":"http://www.gtfs-data-exchange.com/agency/woodburn-transit/","date_added":1329357567,"is_official":1,"dataexchange_id":"woodburn-transit","current_datafile":"woodburn-transit_20130622_0310","id":80,"createdAt":"2013-10-15T20:51:46.000Z","updatedAt":"2013-10-15T20:51:46.000Z"},{"date_last_updated":1377875019,"feed_baseurl":"http://trilliumtransit.com/transit_feeds/yubasutter-ca-us/","name":"Yuba-Sutter Transit","area":"Yuba City","url":"http://www.YubaSutterTransit.com","country":"United States","state":"California","license_url":"","dataexchange_url":"http://www.gtfs-data-exchange.com/agency/yuba-sutter-transit/","date_added":1296463961,"is_official":1,"dataexchange_id":"yuba-sutter-transit","current_datafile":"yuba-sutter-transit_20130830_1503","id":82,"createdAt":"2013-10-15T20:51:46.000Z","updatedAt":"2013-10-15T20:51:46.000Z"},{"date_last_updated":1361334153,"feed_baseurl":"http://gov.allconet.org/ACT/ggl/google_transit.zip","name":"Allegany County Transit","area":"Allegany County","url":"http://gov.allconet.org/act","country":"United States","state":"Maryland","license_url":"","dataexchange_url":"http://www.gtfs-data-exchange.com/agency/allegany-county-transit/","date_added":1297568857,"is_official":1,"dataexchange_id":"allegany-county-transit","current_datafile":"allegany-county-transit_20130220_0422","id":85,"createdAt":"2013-10-16T06:10:53.000Z","updatedAt":"2013-10-16T06:10:53.000Z"},{"date_last_updated":1337629621,"feed_baseurl":"","name":"Ann Arbor Transportation Authority","area":"Ann Arbor","url":"http://www.TheRide.org","country":"United States","state":"Michigan","license_url":"","dataexchange_url":"http://www.gtfs-data-exchange.com/agency/ann-arbor-transportation-authority/","date_added":1231995209,"is_official":1,"dataexchange_id":"ann-arbor-transportation-authority","current_datafile":"ann-arbor-transportation-authority_20120521_1947","id":86,"createdAt":"2013-10-16T06:10:53.000Z","updatedAt":"2013-10-16T06:10:53.000Z"},{"date_last_updated":1264562435,"feed_baseurl":"http://trilliumtransit.com/transit_feeds/sfbay-ferries-ca-us/","name":"Alameda Harbor Bay Ferry","area":"San Francisco Bay Area","url":"http://www.alamedaharborbayferry.com/","country":"United States","state":"California","license_url":"","dataexchange_url":"http://www.gtfs-data-exchange.com/agency/alameda-harbor-bay-ferry/","date_added":1252464906,"is_official":1,"dataexchange_id":"alameda-harbor-bay-ferry","current_datafile":"sfbay-ferries-archiver_20100127_0320","id":87,"createdAt":"2013-10-16T06:10:54.000Z","updatedAt":"2013-10-16T06:10:54.000Z"},{"date_last_updated":1372730801,"feed_baseurl":"http://trilliumtransit.com/transit_feeds/sfbay-ferries-ca-us/","name":"Baylink","area":"San Francisco Bay Area","url":"http://www.baylinkferry.com/","country":"United States","state":"California","license_url":"","dataexchange_url":"http://www.gtfs-data-exchange.com/agency/baylink/","date_added":1252464906,"is_official":1,"dataexchange_id":"baylink","current_datafile":"sfbay-ferries-ca-us-archiver_20130702_0206","id":88,"createdAt":"2013-10-16T06:12:16.000Z","updatedAt":"2013-10-16T06:12:16.000Z"},{"date_last_updated":1372730801,"feed_baseurl":"http://trilliumtransit.com/transit_feeds/sfbay-ferries-ca-us/","name":"Blue & Gold Fleet","area":"San Francisco Bay Area","url":"http://www.blueandgoldfleet.com/","country":"United States","state":"California","license_url":"","dataexchange_url":"http://www.gtfs-data-exchange.com/agency/blue-gold-fleet/","date_added":1252464905,"is_official":1,"dataexchange_id":"blue-gold-fleet","current_datafile":"sfbay-ferries-ca-us-archiver_20130702_0206","id":89,"createdAt":"2013-10-16T06:12:38.000Z","updatedAt":"2013-10-16T06:12:38.000Z"},{"date_last_updated":1357187173,"feed_baseurl":"http://gis.ashevillenc.gov/mapasheville/ashevilletransitfeed/google_transit.zip","name":"Asheville Transit Service","area":"Asheville","url":"http://www.ashevillenc.gov/Departments/Transit.aspx","country":"United States","state":"North Carolina","license_url":"","dataexchange_url":"http://www.gtfs-data-exchange.com/agency/asheville-transit-service/","date_added":1335450520,"is_official":1,"dataexchange_id":"asheville-transit-service","current_datafile":"asheville-transit-service_20130103_0426","id":90,"createdAt":"2013-10-16T06:22:42.000Z","updatedAt":"2013-10-16T06:22:42.000Z"},{"date_last_updated":1361921257,"feed_baseurl":"http://oregon-gtfs.com/gtfs_data/northeast-or-us/","name":"Baker City Community Connection","area":"Baker City","url":"http://www.neotransit.org/Baker/","country":"United States","state":"Oregon","license_url":"","dataexchange_url":"http://www.gtfs-data-exchange.com/agency/baker-city-community-connection/","date_added":1361921257,"is_official":1,"dataexchange_id":"baker-city-community-connection","current_datafile":"matt@trilliumtransit","id":91,"createdAt":"2013-10-16T06:23:06.000Z","updatedAt":"2013-10-16T06:23:06.000Z"},{"date_last_updated":1370057426,"feed_baseurl":"http://bloomington.in.gov/transit/gtfeed/GoogleTransitFeed.zip","name":"Bloomington Transit","area":"Bloomington","url":"http://www.bloomingtontransit.com","country":"United States","state":"Indiana","license_url":"","dataexchange_url":"http://www.gtfs-data-exchange.com/agency/bloomington-transit/","date_added":1351621951,"is_official":1,"dataexchange_id":"bloomington-transit","current_datafile":"bloomington-transit_20130601_0330","id":92,"createdAt":"2013-10-16T06:23:32.000Z","updatedAt":"2013-10-16T06:23:32.000Z"},{"date_last_updated":1361921256,"feed_baseurl":"http://oregon-gtfs.com/gtfs_data/northeast-or-us/","name":"Northeast Oregon Public Transit","area":"La Grande","url":"http://neotransit.org/","country":"United States","state":"Oregon","license_url":"","dataexchange_url":"http://www.gtfs-data-exchange.com/agency/northeast-oregon-public-transit/","date_added":1361921256,"is_official":1,"dataexchange_id":"northeast-oregon-public-transit","current_datafile":"matt@trilliumtransit","id":93,"createdAt":"2013-10-16T08:08:18.000Z","updatedAt":"2013-10-16T08:08:18.000Z"},{"date_last_updated":1338520743,"feed_baseurl":"http://trilliumtransit.com/transit_feeds/clemson-sc-us/","name":"Clemson Area Transit","area":"Clemson","url":"http://www.catbus.com/","country":"United States","state":"South Carolina","license_url":"","dataexchange_url":"http://www.gtfs-data-exchange.com/agency/clemson-area-transit/","date_added":1273716351,"is_official":1,"dataexchange_id":"clemson-area-transit","current_datafile":"clemson-area-transit_20120601_0319","id":94,"createdAt":"2013-10-16T15:04:59.000Z","updatedAt":"2013-10-16T15:04:59.000Z"},{"date_last_updated":1377879285,"feed_baseurl":"http://trilliumtransit.com/transit_feeds/hoodriver-or-us/","name":"Columbia Area Transit","area":"Hood River County","url":"http://community.gorge.net/hrctd/","country":"United States","state":"Oregon","license_url":"","dataexchange_url":"http://www.gtfs-data-exchange.com/agency/columbia-area-transit/","date_added":1259789705,"is_official":1,"dataexchange_id":"columbia-area-transit","current_datafile":"columbia-area-transit_20130830_1614","id":95,"createdAt":"2013-10-16T15:04:59.000Z","updatedAt":"2013-10-16T15:04:59.000Z"},{"date_last_updated":1303619517,"feed_baseurl":"http://maps.gis.co.brown.wi.us/web_documents/Planning/Google_Transit.zip","name":"Green Bay Metro Transit","area":"Green Bay","url":"http://www.ci.green-bay.wi.us/transit/","country":"United States","state":"Wisconsin","license_url":"","dataexchange_url":"http://www.gtfs-data-exchange.com/agency/green-bay-metro-transit/","date_added":1303619517,"is_official":1,"dataexchange_id":"green-bay-metro-transit","current_datafile":"green-bay-metro-transit_20110424_0431","id":96,"createdAt":"2013-10-16T15:05:04.000Z","updatedAt":"2013-10-16T15:05:04.000Z"},{"date_last_updated":1361921257,"feed_baseurl":"http://oregon-gtfs.com/gtfs_data/northeast-or-us/","name":"Wallowa Community Connection","area":"Wallowa","url":"http://www.neotransit.org/Wallowa/Commuter.html","country":"United States","state":"Oregon","license_url":"","dataexchange_url":"http://www.gtfs-data-exchange.com/agency/wallowa-community-connection/","date_added":1361921257,"is_official":1,"dataexchange_id":"wallowa-community-connection","current_datafile":"matt@trilliumtransit","id":97,"createdAt":"2013-10-16T15:05:39.000Z","updatedAt":"2013-10-16T15:05:39.000Z"},{"date_last_updated":1372726557,"feed_baseurl":"http://trilliumtransit.com/transit_feeds/laketahoe-ca-us/","name":"Northstar-at-Tahoe","area":"Tahoe Basin Area","url":"http://www.northstarattahoe.com/info/ski/trip-planning/shuttles.asp","country":"United States","state":"California","license_url":"","dataexchange_url":"http://www.gtfs-data-exchange.com/agency/northstar-at-tahoe/","date_added":1250273030,"is_official":1,"dataexchange_id":"northstar-at-tahoe","current_datafile":"laketahoe-ca-us-archiver_20130702_0055","id":98,"createdAt":"2013-10-16T18:31:20.000Z","updatedAt":"2013-10-16T18:31:20.000Z"},{"date_last_updated":1378084612,"feed_baseurl":"http://www.portauthority.org/GoogleTransitFeed/general_transit.zip","name":"Port Authority of Allegheny County","area":"","url":"http://www.portauthority.org","country":"United States","state":"New York","license_url":"","dataexchange_url":"http://www.gtfs-data-exchange.com/agency/port-authority-of-allegheny-county/","date_added":1263232680,"is_official":1,"dataexchange_id":"port-authority-of-allegheny-county","current_datafile":"port-authority-of-allegheny-county_20130902_0116","id":99,"createdAt":"2013-10-16T18:31:24.000Z","updatedAt":"2013-10-16T18:31:24.000Z"},{"date_last_updated":1378856982,"feed_baseurl":"http://www.sfmta.com/transitdata","name":"San Francisco Municipal Transportation Agency","area":"San Francisco","url":"http://www.sfmta.com","country":"United States","state":"California","license_url":"http://www.sfmta.com/transitdata","dataexchange_url":"http://www.gtfs-data-exchange.com/agency/san-francisco-municipal-transportation-agency/","date_added":1235539672,"is_official":1,"dataexchange_id":"san-francisco-municipal-transportation-agency","current_datafile":"san-francisco-municipal-transportation-agency_20130910_2349","id":100,"createdAt":"2013-10-16T18:31:31.000Z","updatedAt":"2013-10-16T18:31:31.000Z"},{"date_last_updated":1372726558,"feed_baseurl":"http://trilliumtransit.com/transit_feeds/laketahoe-ca-us/","name":"Squaw Valley USA","area":"Tahoe","url":"http://www.squaw.com/getting-squaw-bus","country":"United States","state":"California","license_url":"","dataexchange_url":"http://www.gtfs-data-exchange.com/agency/squaw-valley-usa/","date_added":1262229312,"is_official":1,"dataexchange_id":"squaw-valley-usa","current_datafile":"laketahoe-ca-us-archiver_20130702_0055","id":101,"createdAt":"2013-10-16T18:31:33.000Z","updatedAt":"2013-10-16T18:31:33.000Z"},{"date_last_updated":1379121395,"feed_baseurl":"http://your.kingcounty.gov/extranet/transit/PublicData/GTFS/","name":"Sound Transit","area":"Seattle","url":"http://www.soundtransit.org/","country":"United States","state":"Washington","license_url":"","dataexchange_url":"http://www.gtfs-data-exchange.com/agency/sound-transit/","date_added":1260299405,"is_official":1,"dataexchange_id":"sound-transit","current_datafile":"kingcounty-archiver_20130914_0116","id":102,"createdAt":"2013-10-16T18:31:36.000Z","updatedAt":"2013-10-16T18:31:36.000Z"},{"date_last_updated":1372726557,"feed_baseurl":"http://trilliumtransit.com/transit_feeds/laketahoe-ca-us/","name":"Tahoe Area Regional Transit","area":"Tahoe Basin Area","url":"http://www.placer.ca.gov/Departments/Works/Transit/TART.aspx","country":"United States","state":"California","license_url":"","dataexchange_url":"http://www.gtfs-data-exchange.com/agency/tahoe-area-regional-transit/","date_added":1250273030,"is_official":1,"dataexchange_id":"tahoe-area-regional-transit","current_datafile":"laketahoe-ca-us-archiver_20130702_0055","id":103,"createdAt":"2013-10-16T18:31:36.000Z","updatedAt":"2013-10-16T18:31:36.000Z"},{"date_last_updated":1372726558,"feed_baseurl":"http://trilliumtransit.com/transit_feeds/laketahoe-ca-us/","name":"Town of Truckee","area":"Truckee","url":"http://www.townoftruckee.com/index.aspx?page=53","country":"United States","state":"California","license_url":"","dataexchange_url":"http://www.gtfs-data-exchange.com/agency/town-of-truckee/","date_added":1262229312,"is_official":1,"dataexchange_id":"town-of-truckee","current_datafile":"laketahoe-ca-us-archiver_20130702_0055","id":104,"createdAt":"2013-10-16T18:31:37.000Z","updatedAt":"2013-10-16T18:31:37.000Z"},{"date_last_updated":1366358968,"feed_baseurl":"http://webapps.thebus.org/transitdata/Production","name":"TheBus","area":"Honolulu","url":"http://www.thebus.org","country":"United States","state":"Hawaii","license_url":"http://www.thebus.org/transitfeed/terms-of-use.asp","dataexchange_url":"http://www.gtfs-data-exchange.com/agency/thebus/","date_added":1236408071,"is_official":1,"dataexchange_id":"thebus","current_datafile":"thebus_20130419_0809","id":105,"createdAt":"2013-10-16T18:31:38.000Z","updatedAt":"2013-10-16T18:31:38.000Z"},{"date_last_updated":1377877623,"feed_baseurl":"http://pts.umich.edu/gtfs/google_transit.zip","name":"University of Michigan Transit Services","area":"","url":"http://pts.umich.edu","country":"United States","state":"Michigan","license_url":"","dataexchange_url":"http://www.gtfs-data-exchange.com/agency/university-of-michigan-transit-services/","date_added":1346695408,"is_official":1,"dataexchange_id":"university-of-michigan-transit-services","current_datafile":"university-of-michigan-transit-services_20130830_1547","id":106,"createdAt":"2013-10-16T18:31:40.000Z","updatedAt":"2013-10-16T18:31:40.000Z"},{"date_last_updated":1380663448,"feed_baseurl":"http://developer.rideuta.com/","name":"Utah Transit Authority","area":"Salt Lake City","url":"http://www.rideuta.com/","country":"United States","state":"Utah","license_url":"http://developer.rideuta.com/TermsOfUse.aspx","dataexchange_url":"http://www.gtfs-data-exchange.com/agency/utah-transit-authority/","date_added":1225088022,"is_official":1,"dataexchange_id":"utah-transit-authority","current_datafile":"utah-transit-authority_20131001_2137","id":107,"createdAt":"2013-10-16T18:31:40.000Z","updatedAt":"2013-10-16T18:31:40.000Z"},{"date_last_updated":1378257437,"feed_baseurl":"http://iportal.sacrt.com/GTFS/Unitrans","name":"Unitrans (Davis)","area":"Davis","url":"http://www.unitrans.com","country":"United States","state":"California","license_url":"http://www.sacrt.com/gtfs.stm","dataexchange_url":"http://www.gtfs-data-exchange.com/agency/unitrans-davis/","date_added":1225263497,"is_official":1,"dataexchange_id":"unitrans-davis","current_datafile":"unitrans-davis_20130904_0117","id":108,"createdAt":"2013-10-16T18:31:50.000Z","updatedAt":"2013-10-16T18:31:50.000Z"},{"date_last_updated":0,"feed_baseurl":"http://web.mta.info/developers/data/nyct/subway/google_transit.zip","name":"MTA Subways","area":"New York, New York","url":"","country":"United States","state":"New York","license_url":"","dataexchange_url":"","date_added":0,"is_official":1,"dataexchange_id":"mta-subway","current_datafile":"mta-subway-9_19_14","id":109,"createdAt":"2014-01-21T19:02:31.146Z","updatedAt":"2014-01-21T19:02:31.146Z"}]